{
 "actions": [],
 "allow_rename": 1,
 "creation": "2024-06-15 18:06:44.687033",
 "doctype": "DocType",
 "editable_grid": 1,
 "engine": "InnoDB",
 "field_order": [
  "book_title",
  "status"
 ],
 "fields": [
  {
   "fieldname": "book_title",
   "fieldtype": "Link",
   "in_list_view": 1,
   "label": "Book Title",
   "options": "Book"
  },
  {
   "default": "Pending",
   "fieldname": "status",
   "fieldtype": "Select",
   "in_list_view": 1,
   "label": "status",
   "options": "Complete\nPending",
   "read_only": 1
  }
 ],
 "index_web_pages_for_search": 1,
 "istable": 1,
 "links": [],
 "modified": "2024-09-06 16:43:45.765048",
 "modified_by": "Administrator",
 "module": "Library System",
 "name": "Member Books",
 "owner": "Administrator",
 "permissions": [],
 "sort_field": "creation",
 "sort_order": "DESC",
 "states": []
}